{
	"info": {
		"_postman_id": "f93e540a-997d-414f-b6fa-afd13cfb518f",
		"name": "DevopsMsOrders",
		"schema": "https://schema.getpostman.com/json/collection/v2.1.0/collection.json"
	},
	"item": [
		{
			"name": "Create",
			"request": {
				"method": "POST",
				"header": [],
				"body": {
					"mode": "raw",
					"raw": "[\r\n    \"123\", \"321\", \"111\"\r\n]"
				},
				"url": {
					"raw": "http://localhost:8080/orders",
					"protocol": "http",
					"host": [
						"localhost"
					],
					"port": "8080",
					"path": [
						"orders"
					]
				}
			},
			"response": []
		}
	]
}